MANIFEST.in
README.rst
setup.py
_cffi_build/keccak_build.py
keccak/__init__.py
keccak/_keccak.py
lib/compiler.h
lib/sha3.c
lib/sha3.h
pykeccak.egg-info/PKG-INFO
pykeccak.egg-info/SOURCES.txt
pykeccak.egg-info/dependency_links.txt
pykeccak.egg-info/not-zip-safe
pykeccak.egg-info/requires.txt
pykeccak.egg-info/top_level.txt