Metadata-Version: 1.1
Name: pykeccak
Version: 0.2.0
Summary: Keccak 256 hashing for PyPy2
Home-page: https://github.com/czepluch/pykeccak
Author: Jacob Stenum Czepluch
Author-email: j.czepluch@gmail.com
License: MIT
Platform: UNKNOWN
Classifier: Programming Language :: Python :: 2
Classifier: Programming Language :: Python :: 2.7
Classifier: Programming Language :: Python :: Implementation :: PyPy
